ghmate/__init__.py
ghmate/actions_commands.py
ghmate/additional_commands.py
ghmate/core_commands.py
ghmate/github_client.py
helper_scripts/__init__.py
helper_scripts/build_and_deploy.py
ghmate-1.0.0.dist-info/LICENSE
ghmate-1.0.0.dist-info/METADATA
ghmate-1.0.0.dist-info/WHEEL
ghmate-1.0.0.dist-info/top_level.txt
ghmate-1.0.0.dist-info/RECORD
