Metadata-Version: 2.1
Name: ghmate
Version: 1.0.0
Summary: A Python package for interacting with the GitHub API.
Home-page: https://github.com/serityops/ghmate
License: MIT
Keywords: github,api,package
Classifier: 
Classifier: License :: OSI Approved :: MIT License
Classifier: Programming Language :: Python :: 3
Requires-Python: >=3.8
License-File: LICENSE
